jaqalpaq/scheduler/__init__.py
jaqalpaq/scheduler/scheduler.py
jaqalpaq/transpilers/__init__.py
jaqalpaq/transpilers/cirq/__init__.py
jaqalpaq/transpilers/cirq/frontend.py
jaqalpaq/transpilers/projectq/__init__.py
jaqalpaq/transpilers/projectq/frontend.py
jaqalpaq/transpilers/qiskit/__init__.py
jaqalpaq/transpilers/qiskit/frontend.py
jaqalpaq/transpilers/qiskit/gates.py
jaqalpaq/transpilers/qiskit/instance.py
jaqalpaq/transpilers/qiskit/sampler.py
jaqalpaq/transpilers/quil/__init__.py
jaqalpaq/transpilers/quil/frontend.py
jaqalpaq/transpilers/quil/ioncompiler.py
jaqalpaq/transpilers/quil/qscoutam.py
jaqalpaq/transpilers/tket/__init__.py
jaqalpaq/transpilers/tket/backend.py
jaqalpaq/transpilers/tket/frontend.py
jaqalpaq_extras-1.3.0.data/data/share/jaqalpaq/examples/Tutorials/Transpiler_Demo.ipynb
jaqalpaq_extras-1.3.0.data/data/share/jaqalpaq/tests/test_smoke.py
jaqalpaq_extras-1.3.0.data/data/share/jaqalpaq/tests/scheduler/__init__.py
jaqalpaq_extras-1.3.0.data/data/share/jaqalpaq/tests/scheduler/test_scheduler.py
jaqalpaq_extras-1.3.0.data/data/share/jaqalpaq/tests/transpilers/__init__.py
jaqalpaq_extras-1.3.0.data/data/share/jaqalpaq/tests/transpilers/cirq/__init__.py
jaqalpaq_extras-1.3.0.data/data/share/jaqalpaq/tests/transpilers/cirq/test_cirq_transpiler.py
jaqalpaq_extras-1.3.0.data/data/share/jaqalpaq/tests/transpilers/projectq/__init__.py
jaqalpaq_extras-1.3.0.data/data/share/jaqalpaq/tests/transpilers/projectq/test_projectq_transpiler.py
jaqalpaq_extras-1.3.0.data/data/share/jaqalpaq/tests/transpilers/qiskit/__init__.py
jaqalpaq_extras-1.3.0.data/data/share/jaqalpaq/tests/transpilers/qiskit/test_qiskit_backend.py
jaqalpaq_extras-1.3.0.data/data/share/jaqalpaq/tests/transpilers/qiskit/test_qiskit_gates.py
jaqalpaq_extras-1.3.0.data/data/share/jaqalpaq/tests/transpilers/qiskit/test_qiskit_reverse_transpiler.py
jaqalpaq_extras-1.3.0.data/data/share/jaqalpaq/tests/transpilers/qiskit/test_qiskit_transpiler.py
jaqalpaq_extras-1.3.0.dist-info/licenses/LICENSE
jaqalpaq_extras-1.3.0.dist-info/licenses/NOTICE
jaqalpaq_extras-1.3.0.dist-info/METADATA
jaqalpaq_extras-1.3.0.dist-info/WHEEL
jaqalpaq_extras-1.3.0.dist-info/top_level.txt
jaqalpaq_extras-1.3.0.dist-info/RECORD
